{
    "mode": "triad",
    "count": "5",
    "colors": [
        {
            "hex": {
                "value": "#C1239D",
                "clean": "C1239D"
            },
            "rgb": {
                "fraction": {
                    "r": 0.7568627450980392,
                    "g": 0.13725490196078433,
                    "b": 0.615686274509804
                },
                "r": 193,
                "g": 35,
                "b": 157,
                "value": "rgb(193, 35, 157)"
            },
            "hsl": {
                "fraction": {
                    "h": 0.871308016877637,
                    "s": 0.6929824561403509,
                    "l": 0.44705882352941173
                },
                "h": 314,
                "s": 69,
                "l": 45,
                "value": "hsl(314, 69%, 45%)"
            },
            "hsv": {
                "fraction": {
                    "h": 0.871308016877637,
                    "s": 0.8186528497409327,
                    "v": 0.7568627450980392
                },
                "value": "hsv(314, 82%, 76%)",
                "h": 314,
                "s": 82,
                "v": 76
            },
            "name": {
                "value": "Cerise",
                "closest_named_hex": "#DA3287",
                "exact_match_name": false,
                "distance": 2460
            },
            "cmyk": {
                "fraction": {
                    "c": 0,
                    "m": 0.8186528497409327,
                    "y": 0.18652849740932637,
                    "k": 0.2431372549019608
                },
                "value": "cmyk(0, 82, 19, 24)",
                "c": 0,
                "m": 82,
                "y": 19,
                "k": 24
            },
            "XYZ": {
                "fraction": {
                    "X": 0.4723439215686274,
                    "Y": 0.3035262745098039,
                    "Z": 0.6161780392156863
                },
                "value": "XYZ(47, 30, 62)",
                "X": 47,
                "Y": 30,
                "Z": 62
            },
            "image": {
                "bare": "https://www.thecolorapi.com/id?format=svg&named=false&hex=C1239D",
                "named": "https://www.thecolorapi.com/id?format=svg&hex=C1239D"
            },
            "contrast": {
                "value": "#ffffff"
            },
            "_links": {
                "self": {
                    "href": "/id?hex=C1239D"
                }
            },
            "_embedded": {}
        },
        {
            "hex": {
                "value": "#A0CE22",
                "clean": "A0CE22"
            },
            "rgb": {
                "fraction": {
                    "r": 0.6274509803921569,
                    "g": 0.807843137254902,
                    "b": 0.13333333333333333
                },
                "r": 160,
                "g": 206,
                "b": 34,
                "value": "rgb(160, 206, 34)"
            },
            "hsl": {
                "fraction": {
                    "h": 0.21124031007751942,
                    "s": 0.7166666666666667,
                    "l": 0.47058823529411764
                },
                "h": 76,
                "s": 72,
                "l": 47,
                "value": "hsl(76, 72%, 47%)"
            },
            "hsv": {
                "fraction": {
                    "h": 0.21124031007751942,
                    "s": 0.8349514563106797,
                    "v": 0.807843137254902
                },
                "value": "hsv(76, 83%, 81%)",
                "h": 76,
                "s": 83,
                "v": 81
            },
            "name": {
                "value": "Atlantis",
                "closest_named_hex": "#97CD2D",
                "exact_match_name": false,
                "distance": 993
            },
            "cmyk": {
                "fraction": {
                    "c": 0.22330097087378645,
                    "m": 0,
                    "y": 0.8349514563106797,
                    "k": 0.19215686274509802
                },
                "value": "cmyk(22, 0, 83, 19)",
                "c": 22,
                "m": 0,
                "y": 83,
                "k": 19
            },
            "XYZ": {
                "fraction": {
                    "X": 0.571712156862745,
                    "Y": 0.7207921568627451,
                    "Z": 0.23513803921568627
                },
                "value": "XYZ(57, 72, 24)",
                "X": 57,
                "Y": 72,
                "Z": 24
            },
            "image": {
                "bare": "https://www.thecolorapi.com/id?format=svg&named=false&hex=A0CE22",
                "named": "https://www.thecolorapi.com/id?format=svg&hex=A0CE22"
            },
            "contrast": {
                "value": "#000000"
            },
            "_links": {
                "self": {
                    "href": "/id?hex=A0CE22"
                }
            },
            "_embedded": {}
        },
        {
            "hex": {
                "value": "#21AEDD",
                "clean": "21AEDD"
            },
            "rgb": {
                "fraction": {
                    "r": 0.12941176470588237,
                    "g": 0.6823529411764706,
                    "b": 0.8666666666666667
                },
                "r": 33,
                "g": 174,
                "b": 221,
                "value": "rgb(33, 174, 221)"
            },
            "hsl": {
                "fraction": {
                    "h": 0.5416666666666666,
                    "s": 0.7401574803149606,
                    "l": 0.4980392156862745
                },
                "h": 195,
                "s": 74,
                "l": 50,
                "value": "hsl(195, 74%, 50%)"
            },
            "hsv": {
                "fraction": {
                    "h": 0.5416666666666666,
                    "s": 0.8506787330316742,
                    "v": 0.8666666666666667
                },
                "value": "hsv(195, 85%, 87%)",
                "h": 195,
                "s": 85,
                "v": 87
            },
            "name": {
                "value": "Cerulean",
                "closest_named_hex": "#1DACD6",
                "exact_match_name": false,
                "distance": 215
            },
            "cmyk": {
                "fraction": {
                    "c": 0.8506787330316742,
                    "m": 0.21266968325791855,
                    "y": 0,
                    "k": 0.1333333333333333
                },
                "value": "cmyk(85, 21, 0, 13)",
                "c": 85,
                "m": 21,
                "y": 0,
                "k": 13
            },
            "XYZ": {
                "fraction": {
                    "X": 0.4538121568627451,
                    "Y": 0.5781050980392157,
                    "Z": 0.9076007843137256
                },
                "value": "XYZ(45, 58, 91)",
                "X": 45,
                "Y": 58,
                "Z": 91
            },
            "image": {
                "bare": "https://www.thecolorapi.com/id?format=svg&named=false&hex=21AEDD",
                "named": "https://www.thecolorapi.com/id?format=svg&hex=21AEDD"
            },
            "contrast": {
                "value": "#000000"
            },
            "_links": {
                "self": {
                    "href": "/id?hex=21AEDD"
                }
            },
            "_embedded": {}
        },
        {
            "hex": {
                "value": "#28B4E2",
                "clean": "28B4E2"
            },
            "rgb": {
                "fraction": {
                    "r": 0.1568627450980392,
                    "g": 0.7058823529411765,
                    "b": 0.8862745098039215
                },
                "r": 40,
                "g": 180,
                "b": 226,
                "value": "rgb(40, 180, 226)"
            },
            "hsl": {
                "fraction": {
                    "h": 0.5412186379928314,
                    "s": 0.7622950819672131,
                    "l": 0.5215686274509803
                },
                "h": 195,
                "s": 76,
                "l": 52,
                "value": "hsl(195, 76%, 52%)"
            },
            "hsv": {
                "fraction": {
                    "h": 0.5412186379928314,
                    "s": 0.8230088495575221,
                    "v": 0.8862745098039215
                },
                "value": "hsv(195, 82%, 89%)",
                "h": 195,
                "s": 82,
                "v": 89
            },
            "name": {
                "value": "Cerulean",
                "closest_named_hex": "#1DACD6",
                "exact_match_name": false,
                "distance": 573
            },
            "cmyk": {
                "fraction": {
                    "c": 0.8230088495575221,
                    "m": 0.20353982300884946,
                    "y": 0,
                    "k": 0.11372549019607847
                },
                "value": "cmyk(82, 20, 0, 11)",
                "c": 82,
                "m": 20,
                "y": 0,
                "k": 11
            },
            "XYZ": {
                "fraction": {
                    "X": 0.4770862745098039,
                    "Y": 0.6021850980392156,
                    "Z": 0.9295725490196078
                },
                "value": "XYZ(48, 60, 93)",
                "X": 48,
                "Y": 60,
                "Z": 93
            },
            "image": {
                "bare": "https://www.thecolorapi.com/id?format=svg&named=false&hex=28B4E2",
                "named": "https://www.thecolorapi.com/id?format=svg&hex=28B4E2"
            },
            "contrast": {
                "value": "#000000"
            },
            "_links": {
                "self": {
                    "href": "/id?hex=28B4E2"
                }
            },
            "_embedded": {}
        },
        {
            "hex": {
                "value": "#30B9E7",
                "clean": "30B9E7"
            },
            "rgb": {
                "fraction": {
                    "r": 0.18823529411764706,
                    "g": 0.7254901960784313,
                    "b": 0.9058823529411765
                },
                "r": 48,
                "g": 185,
                "b": 231,
                "value": "rgb(48, 185, 231)"
            },
            "hsl": {
                "fraction": {
                    "h": 0.5418943533697631,
                    "s": 0.7922077922077921,
                    "l": 0.5470588235294118
                },
                "h": 195,
                "s": 79,
                "l": 55,
                "value": "hsl(195, 79%, 55%)"
            },
            "hsv": {
                "fraction": {
                    "h": 0.5418943533697631,
                    "s": 0.7922077922077922,
                    "v": 0.9058823529411765
                },
                "value": "hsv(195, 79%, 91%)",
                "h": 195,
                "s": 79,
                "v": 91
            },
            "name": {
                "value": "Picton Blue",
                "closest_named_hex": "#45B1E8",
                "exact_match_name": false,
                "distance": 798
            },
            "cmyk": {
                "fraction": {
                    "c": 0.7922077922077922,
                    "m": 0.19913419913419916,
                    "y": 0,
                    "k": 0.09411764705882353
                },
                "value": "cmyk(79, 20, 0, 9)",
                "c": 79,
                "m": 20,
                "y": 0,
                "k": 9
            },
            "XYZ": {
                "fraction": {
                    "X": 0.5005752941176471,
                    "Y": 0.6242941176470588,
                    "Z": 0.9511525490196078
                },
                "value": "XYZ(50, 62, 95)",
                "X": 50,
                "Y": 62,
                "Z": 95
            },
            "image": {
                "bare": "https://www.thecolorapi.com/id?format=svg&named=false&hex=30B9E7",
                "named": "https://www.thecolorapi.com/id?format=svg&hex=30B9E7"
            },
            "contrast": {
                "value": "#000000"
            },
            "_links": {
                "self": {
                    "href": "/id?hex=30B9E7"
                }
            },
            "_embedded": {}
        }
    ],
    "seed": {
        "hex": {
            "value": "#24B1E0",
            "clean": "24B1E0"
        },
        "rgb": {
            "fraction": {
                "r": 0.1411764705882353,
                "g": 0.6941176470588235,
                "b": 0.8784313725490196
            },
            "r": 36,
            "g": 177,
            "b": 224,
            "value": "rgb(36, 177, 224)"
        },
        "hsl": {
            "fraction": {
                "h": 0.5416666666666666,
                "s": 0.752,
                "l": 0.5098039215686274
            },
            "h": 195,
            "s": 75,
            "l": 51,
            "value": "hsl(195, 75%, 51%)"
        },
        "hsv": {
            "fraction": {
                "h": 0.5416666666666666,
                "s": 0.8392857142857143,
                "v": 0.8784313725490196
            },
            "value": "hsv(195, 84%, 88%)",
            "h": 195,
            "s": 84,
            "v": 88
        },
        "name": {
            "value": "Cerulean",
            "closest_named_hex": "#1DACD6",
            "exact_match_name": false,
            "distance": 356
        },
        "cmyk": {
            "fraction": {
                "c": 0.8392857142857143,
                "m": 0.20982142857142858,
                "y": 0,
                "k": 0.1215686274509804
            },
            "value": "cmyk(84, 21, 0, 12)",
            "c": 84,
            "m": 21,
            "y": 0,
            "k": 12
        },
        "XYZ": {
            "fraction": {
                "X": 0.46499450980392154,
                "Y": 0.5898698039215686,
                "Z": 0.9204125490196079
            },
            "value": "XYZ(46, 59, 92)",
            "X": 46,
            "Y": 59,
            "Z": 92
        },
        "image": {
            "bare": "https://www.thecolorapi.com/id?format=svg&named=false&hex=24B1E0",
            "named": "https://www.thecolorapi.com/id?format=svg&hex=24B1E0"
        },
        "contrast": {
            "value": "#000000"
        },
        "_links": {
            "self": {
                "href": "/id?hex=24B1E0"
            }
        },
        "_embedded": {}
    },
    "image": {
        "bare": "https://www.thecolorapi.com/scheme?format=svg&named=false&hex=24B1E0&mode=triad&count=5",
        "named": "https://www.thecolorapi.com/scheme?format=svg&hex=24B1E0&mode=triad&count=5"
    },
    "_links": {
        "self": "/scheme?hex=24B1E0&mode=triad&count=5",
        "schemes": {
            "monochrome": "/scheme?hex=24B1E0&mode=monochrome&count=5",
            "monochrome-dark": "/scheme?hex=24B1E0&mode=monochrome-dark&count=5",
            "monochrome-light": "/scheme?hex=24B1E0&mode=monochrome-light&count=5",
            "analogic": "/scheme?hex=24B1E0&mode=analogic&count=5",
            "complement": "/scheme?hex=24B1E0&mode=complement&count=5",
            "analogic-complement": "/scheme?hex=24B1E0&mode=analogic-complement&count=5",
            "triad": "/scheme?hex=24B1E0&mode=triad&count=5",
            "quad": "/scheme?hex=24B1E0&mode=quad&count=5"
        }
    },
    "_embedded": {}
}